jschon/__init__.py
jschon/exceptions.py
jschon/json.py
jschon/jsonpointer.py
jschon/jsonschema.py
jschon/output.py
jschon/uri.py
jschon/utils.py
jschon/catalogue/_2019_09.py
jschon/catalogue/_2020_12.py
jschon/catalogue/__init__.py
jschon/catalogue/json-schema-spec-2019-09/hyper-schema.json
jschon/catalogue/json-schema-spec-2019-09/links.json
jschon/catalogue/json-schema-spec-2019-09/schema.json
jschon/catalogue/json-schema-spec-2019-09/meta/applicator.json
jschon/catalogue/json-schema-spec-2019-09/meta/content.json
jschon/catalogue/json-schema-spec-2019-09/meta/core.json
jschon/catalogue/json-schema-spec-2019-09/meta/format.json
jschon/catalogue/json-schema-spec-2019-09/meta/hyper-schema.json
jschon/catalogue/json-schema-spec-2019-09/meta/meta-data.json
jschon/catalogue/json-schema-spec-2019-09/meta/validation.json
jschon/catalogue/json-schema-spec-2019-09/output/hyper-schema.json
jschon/catalogue/json-schema-spec-2019-09/output/schema.json
jschon/catalogue/json-schema-spec-2019-09/output/verbose-example.json
jschon/catalogue/json-schema-spec-2020-12/schema.json
jschon/catalogue/json-schema-spec-2020-12/archive/hyper-schema.json
jschon/catalogue/json-schema-spec-2020-12/archive/links.json
jschon/catalogue/json-schema-spec-2020-12/archive/meta/hyper-schema.json
jschon/catalogue/json-schema-spec-2020-12/meta/applicator.json
jschon/catalogue/json-schema-spec-2020-12/meta/content.json
jschon/catalogue/json-schema-spec-2020-12/meta/core.json
jschon/catalogue/json-schema-spec-2020-12/meta/format-annotation.json
jschon/catalogue/json-schema-spec-2020-12/meta/format-assertion.json
jschon/catalogue/json-schema-spec-2020-12/meta/meta-data.json
jschon/catalogue/json-schema-spec-2020-12/meta/unevaluated.json
jschon/catalogue/json-schema-spec-2020-12/meta/validation.json
jschon/catalogue/json-schema-spec-2020-12/output/hyper-schema.json
jschon/catalogue/json-schema-spec-2020-12/output/schema.json
jschon/catalogue/json-schema-spec-2020-12/output/verbose-example.json
jschon_shamelessdowngrade-0.7.0.dist-info/LICENSE
jschon_shamelessdowngrade-0.7.0.dist-info/METADATA
jschon_shamelessdowngrade-0.7.0.dist-info/WHEEL
jschon_shamelessdowngrade-0.7.0.dist-info/top_level.txt
jschon_shamelessdowngrade-0.7.0.dist-info/RECORD
